biov/__init__.py
biov/_patch.py
biov/config.py
biov/dataframe.py
biov/seq.py
biov/executables/__init__.py
biov/executables/_blat.py
biov/io/__init__.py
biov/io/_preprocess.py
biov/io/fastx.py
biov/io/gff.py
biov-0.1.2.dist-info/METADATA
biov-0.1.2.dist-info/WHEEL
biov-0.1.2.dist-info/entry_points.txt
biov-0.1.2.dist-info/RECORD
