Metadata-Version: 2.4
Name: biov
Version: 0.1.2
Summary: Next-generation development experience for computational molecular biology.
Author-email: Tang Ziya <tcztzy@gmail.Com>
Requires-Python: >=3.11
Requires-Dist: biopython>=1.85
Requires-Dist: fsspec[full]>=2025.3.2
Requires-Dist: pandas>=2.2.3
Requires-Dist: pydantic-settings>=2.8.1
Requires-Dist: typeguard>=4.4.2
Requires-Dist: typer>=0.15.2
Requires-Dist: typing-extensions>=4.13.2
